qemu_compose/__init__.py
qemu_compose/local_store.py
qemu_compose/log_tool.py
qemu_compose/main.py
qemu_compose/cmd/__init__.py
qemu_compose/cmd/images_command.py
qemu_compose/cmd/ps_command.py
qemu_compose/cmd/run_command.py
qemu_compose/cmd/start_command.py
qemu_compose/image/__init__.py
qemu_compose/image/manifest.py
qemu_compose/instance/__init__.py
qemu_compose/instance/http.py
qemu_compose/instance/name.py
qemu_compose/instance/qemu_runner.py
qemu_compose/instance/terminal.py
qemu_compose/qemu/__init__.py
qemu_compose/qemu/machine/__init__.py
qemu_compose/qemu/machine/console_socket.py
qemu_compose/qemu/machine/machine.py
qemu_compose/qemu/machine/py.typed
qemu_compose/qemu/machine/qtest.py
qemu_compose/qemu/qmp/__init__.py
qemu_compose/qemu/qmp/error.py
qemu_compose/qemu/qmp/events.py
qemu_compose/qemu/qmp/legacy.py
qemu_compose/qemu/qmp/message.py
qemu_compose/qemu/qmp/models.py
qemu_compose/qemu/qmp/protocol.py
qemu_compose/qemu/qmp/py.typed
qemu_compose/qemu/qmp/qmp_client.py
qemu_compose/qemu/qmp/qmp_shell.py
qemu_compose/qemu/qmp/qmp_tui.py
qemu_compose/qemu/qmp/util.py
qemu_compose/qemu/utils/__init__.py
qemu_compose/qemu/utils/accel.py
qemu_compose/qemu/utils/py.typed
qemu_compose/qemu/utils/qemu_ga_client.py
qemu_compose/qemu/utils/qom.py
qemu_compose/qemu/utils/qom_common.py
qemu_compose/qemu/utils/qom_fuse.py
qemu_compose/utils/__init__.py
qemu_compose/utils/hostnames.py
qemu_compose/utils/human_readable.py
qemu_compose/utils/jsonlisp.py
qemu_compose/utils/names_gen.py
qemu_compose/utils/utcdatetime.py
qemu_compose/utils/vsock.py
qemu_compose/utils/zio.py
qemu_compose-0.8.7.dist-info/METADATA
qemu_compose-0.8.7.dist-info/WHEEL
qemu_compose-0.8.7.dist-info/entry_points.txt
qemu_compose-0.8.7.dist-info/licenses/LICENSE.txt
qemu_compose-0.8.7.dist-info/RECORD
