Metadata-Version: 2.4
Name: qemu-compose
Version: 0.8.7
Summary: docker-compose style composer for qemu
Author-email: Wenlei Zhu <i@ztrix.me>, Zhen Tang <tangzhen23@foxmail.com>
License-File: LICENSE.txt
Keywords: qemu,qemu-compose,qemu_compose
Classifier: Development Status :: 4 - Beta
Classifier: Environment :: Console
Classifier: Operating System :: POSIX
Classifier: Programming Language :: Python :: 3
Classifier: Programming Language :: Python :: 3.8
Classifier: Programming Language :: Python :: 3.9
Classifier: Programming Language :: Python :: 3.10
Classifier: Programming Language :: Python :: 3.11
Classifier: Programming Language :: Python :: 3.12
Classifier: Programming Language :: Python :: 3.13
Classifier: Programming Language :: Python :: 3.14
Classifier: Topic :: Internet
Classifier: Topic :: Utilities
Requires-Python: >=3.8
Requires-Dist: pycryptodome>=3.20.0
Requires-Dist: pyyaml>=6.0.0
